gridchen/__init__.py
gridchen/converter.js
gridchen/editor.js
gridchen/gridchen-internal.d.ts
gridchen/gridchen.d.ts
gridchen/index.js
gridchen/json_patch_merge.js
gridchen/matrixview.js
gridchen/package.json
gridchen/plotly_wrapper.js
gridchen/selection.js
gridchen/utils.js
gridchen/webcomponent.js
gridchen/testing/__init__.py
gridchen/testing/runner.js
gridchen/testing/suite.js
gridchen/testing/utils.js
gridchen/tests/config.js
gridchen/tests/test_Clipboard.js
gridchen/tests/test_Converter.js
gridchen/tests/test_DataViews.js
gridchen/tests/test_GridChen.js
gridchen/tests/test_date.js
gridchen/tests/test_json_patch_merge.js
gridchen/tests/test_patch.js
gridchen/tests/test_range.js
gridchen/tests/test_selection.js
gridchen/tests/test_tsvToMatrix.js
gridchen-0.1.5.dist-info/LICENSE
gridchen-0.1.5.dist-info/METADATA
gridchen-0.1.5.dist-info/WHEEL
gridchen-0.1.5.dist-info/top_level.txt
gridchen-0.1.5.dist-info/RECORD
