Metadata-Version: 2.1
Name: gridchen
Version: 0.1.5
Summary: Very lightweight and fast editable web grid with strict MS-Excel adherence to user experience.
Home-page: https://github.com/decatur/grid-chen
Author: Wolfgang Kühn
License: UNKNOWN
Platform: UNKNOWN
Requires-Python: >=3.6,<4.0
